__init__.py
pitechcar/__init__.py
pitechcar/car.py
pitechcar/cli/__init__.py
pitechcar/cli/run_car.py
pitechcar/hardware/__init__.py
pitechcar/hardware/mcp3201.py
pitechcar/hardware/motor_driver.py
pitechcar/hardware/pihut_controller.py
pitechcar/hardware/pwm_controller.py
pitechcar/modules/__init__.py
pitechcar/modules/battery_monitor.py
pitechcar/modules/wifi_monitor.py
sfz_pitechcar-1.0.0.dist-info/licenses/LICENCE
sfz_pitechcar-1.0.0.dist-info/METADATA
sfz_pitechcar-1.0.0.dist-info/WHEEL
sfz_pitechcar-1.0.0.dist-info/entry_points.txt
sfz_pitechcar-1.0.0.dist-info/top_level.txt
sfz_pitechcar-1.0.0.dist-info/RECORD
