Metadata-Version: 2.4
Name: sfz-pitechcar
Version: 1.0.0
Summary: Control software for remote Fischertechnik Maker Car with SFZ PCB.
Author: Falko Schmidt
Project-URL: Repository, https://gitlab.com/F-Schmidt/sfz-pitechcar.git
Requires-Python: >=3.7
License-File: LICENCE
Requires-Dist: approxeng.input==2.6.4
Requires-Dist: adafruit-python-shell==1.11.1
Requires-Dist: adafruit-circuitpython-pca9685==3.4.20
Requires-Dist: adafruit-circuitpython-servokit==1.3.22
Requires-Dist: adafruit-circuitpython-mcp3xxx==1.5.0
Dynamic: license-file
